homie/__init__.py
homie/device_base.py
homie/device_boolean.py
homie/device_button.py
homie/device_contact.py
homie/device_dimmer.py
homie/device_integer.py
homie/device_speed.py
homie/device_state.py
homie/device_status.py
homie/device_switch.py
homie/device_temperature.py
homie/device_temperature_humidity.py
homie/device_temperature_humidity_battery.py
homie/device_thermostat.py
homie/mqtt/__init__.py
homie/mqtt/gmqtt_client.py
homie/mqtt/homie_mqtt_client.py
homie/mqtt/mqtt_base.py
homie/mqtt/paho_mqtt_client.py
homie/node/__init__.py
homie/node/node_base.py
homie/node/node_boolean.py
homie/node/node_contact.py
homie/node/node_dimmer.py
homie/node/node_integer.py
homie/node/node_state.py
homie/node/node_switch.py
homie/node/property/__init__.py
homie/node/property/property_base.py
homie/node/property/property_battery.py
homie/node/property/property_boolean.py
homie/node/property/property_button.py
homie/node/property/property_color.py
homie/node/property/property_contact.py
homie/node/property/property_datetime.py
homie/node/property/property_dimmer.py
homie/node/property/property_enum.py
homie/node/property/property_float.py
homie/node/property/property_humidity.py
homie/node/property/property_integer.py
homie/node/property/property_pressure.py
homie/node/property/property_setpoint.py
homie/node/property/property_speed.py
homie/node/property/property_string.py
homie/node/property/property_switch.py
homie/node/property/property_temperature.py
homie/support/__init__.py
homie/support/helpers.py
homie/support/network_information.py
homie/support/repeating_timer.py
Homie4-0.4.0.dist-info/LICENSE
Homie4-0.4.0.dist-info/METADATA
Homie4-0.4.0.dist-info/WHEEL
Homie4-0.4.0.dist-info/top_level.txt
Homie4-0.4.0.dist-info/RECORD
