Metadata-Version: 2.1
Name: Homie4
Version: 0.4.0
Summary: Homie 4.0.0 Implementation
Home-page: https://github.com/mjcumming/homie4
Author: Michael Cumming
Author-email: mike@4831.com
Keywords: HOMIE,MQTT
Classifier: Development Status :: 5 - Production/Stable
Classifier: Programming Language :: Python :: 3
Classifier: License :: OSI Approved :: MIT License
Classifier: Operating System :: OS Independent
License-File: LICENSE
Requires-Dist: paho-mqtt (>=1.3.0)
